my_awesome_eda/__init__.py
my_awesome_eda/categories.py
my_awesome_eda/customization.py
my_awesome_eda/myawesomeeda.py
my_awesome_eda/version.py
my_awesome_eda/visualization.py
myawesomeeda-1.0.1.dist-info/licenses/LICENSE
myawesomeeda-1.0.1.dist-info/METADATA
myawesomeeda-1.0.1.dist-info/WHEEL
myawesomeeda-1.0.1.dist-info/top_level.txt
myawesomeeda-1.0.1.dist-info/RECORD
