Metadata-Version: 2.4
Name: myawesomeeda
Version: 1.0.1
Summary: 📊Simple yet cool EDA module
Home-page: https://github.com/iliapopov17/MyAwesomeEDA
Author: Ilia Popov
Author-email: iljapopov17@gmail.com
Classifier: Programming Language :: Python :: 3
Classifier: License :: OSI Approved :: MIT License
Classifier: Operating System :: OS Independent
Requires-Python: >=3.6
License-File: LICENSE
Requires-Dist: ipython==9.3.0
Requires-Dist: matplotlib==3.10.3
Requires-Dist: matplotlib-inline==0.1.7
Requires-Dist: numpy==2.3.0
Requires-Dist: pandas==2.3.0
Requires-Dist: seaborn==0.13.2
Requires-Dist: ipykernel==6.29.5
Dynamic: author
Dynamic: author-email
Dynamic: classifier
Dynamic: description
Dynamic: description-content-type
Dynamic: home-page
Dynamic: license-file
Dynamic: requires-dist
Dynamic: requires-python
Dynamic: summary
